diamond_bandalyzer/__init__.py
diamond_bandalyzer/defects.py
diamond_bandalyzer/diamondsoln.py
diamond_bandalyzer/differentiationStencil.py
diamond_bandalyzer/fundementalconstants.py
diamond_bandalyzer/plotter.py
diamond_bandalyzer/poissonNRsolver.py
diamond_bandalyzer/poissonequations.py
diamond_bandalyzer/poissonrelaxationsolver.py
diamond_bandalyzer/schrodpoissonNRsolver.py
diamond_bandalyzer/schrodpoissonNRsolver2.py
diamond_bandalyzer/schrodpoissonequations.py
diamond_bandalyzer/settingsobject.py
diamond_bandalyzer/solver.py
diamond_bandalyzer/utilities.py
diamond_bandalyzer/version.py
diamond_bandalyzer/.config/default_settings.ini
diamond_bandalyzer/.config/defect_library.ini
diamond_bandalyzer/.config/example_defects.ini
diamond_bandalyzer/cli/__init__.py
diamond_bandalyzer/cli/__main__.py
diamond_bandalyzer/cli/functions.py
diamond_bandalyzer/validation_tests/__init__.py
diamond_bandalyzer/validation_tests/bulk_Ef.py
diamond_bandalyzer/validation_tests/intrinsic_test.py
diamond_bandalyzer/validation_tests/z_shift_test.py
diamond_bandalyzer/validation_tests/z_shift_test/defects.ini
diamond_bandalyzer/validation_tests/z_shift_test/settings.ini
diamond_bandalyzer-0.4.1.dist-info/LICENCE
diamond_bandalyzer-0.4.1.dist-info/METADATA
diamond_bandalyzer-0.4.1.dist-info/WHEEL
diamond_bandalyzer-0.4.1.dist-info/entry_points.txt
diamond_bandalyzer-0.4.1.dist-info/top_level.txt
diamond_bandalyzer-0.4.1.dist-info/RECORD
