Metadata-Version: 2.1
Name: diamond-bandalyzer
Version: 0.4.1
Summary: A free, open-source python package for solving the near surface diamond electronic band structure.
Home-page: UNKNOWN
Author: Nikolai Dontschuk, Daniel McCloskey
Author-email: dontschuk.n@unimelb.edu.au
License: AFLv3
Platform: UNKNOWN
Requires-Python: >3.6
Requires-Dist: Click
Requires-Dist: numpy
Requires-Dist: scipy
Requires-Dist: numba
Requires-Dist: matplotlib
Requires-Dist: fdint
Requires-Dist: numpyencoder
Requires-Dist: tqdm
